compare_file_diff/__init__.py
compare_file_diff/compare_files.py
pycmpfiles-0.0.1.dist-info/LICENSE
pycmpfiles-0.0.1.dist-info/METADATA
pycmpfiles-0.0.1.dist-info/WHEEL
pycmpfiles-0.0.1.dist-info/top_level.txt
pycmpfiles-0.0.1.dist-info/RECORD
