Metadata-Version: 2.1
Name: pycmpfiles
Version: 0.0.1
Summary: A small example package which is used to compare two file and show the difference
Author-email: Palla Gangadhar Laxminarayan <ganga11497@gmail.com>
Project-URL: Homepage, https://github.com/PallaGangadhar/CompareFiles.git
Classifier: Programming Language :: Python :: 3
Classifier: License :: OSI Approved :: MIT License
Classifier: Operating System :: OS Independent
Requires-Python: >=3.9
License-File: LICENSE
